cat_aspect_extraction/__init__.py
cat_aspect_extraction/attention.py
cat_aspect_extraction/cat.py
cat_aspect_extraction-2.0.1.dist-info/licenses/LICENSE
cat_aspect_extraction-2.0.1.dist-info/METADATA
cat_aspect_extraction-2.0.1.dist-info/WHEEL
cat_aspect_extraction-2.0.1.dist-info/top_level.txt
cat_aspect_extraction-2.0.1.dist-info/RECORD
