Metadata-Version: 2.4
Name: cat-aspect-extraction
Version: 2.0.1
Summary: Aspect extraction based on word embeddings
Author-email: Marc-Alexis Azaïs <azaismarc.pro@gmail.com>
Project-URL: Repository, https://github.com/azaismarc/cat-aspect-extraction.git
Project-URL: Repository (original), https://github.com/clips/cat/
Project-URL: Paper, https://aclanthology.org/2020.acl-main.290/
Keywords: cat,nlp,absa,topic modeling,sentiment analysis,aspect extraction,BERTopic,lda,top2vec,word2vec
Classifier: Development Status :: 5 - Production/Stable
Classifier: Intended Audience :: Science/Research
Classifier: Intended Audience :: Developers
Classifier: Intended Audience :: Customer Service
Classifier: Topic :: Text Processing
Classifier: Topic :: Scientific/Engineering :: Artificial Intelligence
Classifier: License :: OSI Approved :: GNU General Public License v3 or later (GPLv3+)
Classifier: Programming Language :: Python :: 3
License-File: LICENSE
Requires-Dist: reach
Requires-Dist: numpy
Requires-Dist: scikit-learn
Dynamic: license-file
